magia/__init__.py
magia/bundle.py
magia/constants.py
magia/core.py
magia/external.py
magia/memory.py
magia/module.py
magia/std/__init__.py
magia/std/bundles.py
magia/std/encoding.py
magia/std/fixed_point.py
magia/std/storage.py
syn_magia-0.3.0.dist-info/LICENSE
syn_magia-0.3.0.dist-info/METADATA
syn_magia-0.3.0.dist-info/WHEEL
syn_magia-0.3.0.dist-info/RECORD
